{
    "image": "/enemies/hypnoWorm.png",
    "width": 50,
    "height": 60,
    "x": 0,
    "y": 0,
    "animations": {
        "move": {
            "worm_0":
            {
                "frame": {"x":7,"y":129,"w":44,"h":17},
                "rotated": false,
                "trimmed": false,
                "spriteSourceSize": {"x":0,"y":0,"w":64,"h":65},
                "sourceSize": {"w":64,"h":63}
            },
            "worm_1":
            {
                "frame": {"x":51,"y":129,"w":44,"h":17},
                "rotated": false,
                "trimmed": false,
                "spriteSourceSize": {"x":0,"y":0,"w":64,"h":65},
                "sourceSize": {"w":64,"h":63}
            },
            "worm_2":
            {
                "frame": {"x":95,"y":129,"w":44,"h":17},
                "rotated": false,
                "trimmed": false,
                "spriteSourceSize": {"x":0,"y":0,"w":64,"h":65},
                "sourceSize": {"w":64,"h":63}
            },
            "worm_3":
            {
                "frame": {"x":141,"y":129,"w":44,"h":17},
                "rotated": false,
                "trimmed": false,
                "spriteSourceSize": {"x":0,"y":0,"w":64,"h":65},
                "sourceSize": {"w":64,"h":63}
            },
            "worm_4":
            {
                "frame": {"x":190,"y":129,"w":44,"h":17},
                "rotated": false,
                "trimmed": false,
                "spriteSourceSize": {"x":0,"y":0,"w":64,"h":65},
                "sourceSize": {"w":64,"h":63}
            },
            "worm_5":
            {
                "frame": {"x":243,"y":129,"w":44,"h":17},
                "rotated": false,
                "trimmed": false,
                "spriteSourceSize": {"x":0,"y":0,"w":64,"h":65},
                "sourceSize": {"w":64,"h":63}
            },
            "worm_6":
            {
                "frame": {"x":295,"y":129,"w":44,"h":17},
                "rotated": false,
                "trimmed": false,
                "spriteSourceSize": {"x":0,"y":0,"w":64,"h":65},
                "sourceSize": {"w":64,"h":63}
            },
            "worm_7":
            {
                "frame": {"x":343,"y":129,"w":44,"h":17},
                "rotated": false,
                "trimmed": false,
                "spriteSourceSize": {"x":0,"y":0,"w":64,"h":65},
                "sourceSize": {"w":64,"h":63}
            },
            "worm_8":
            {
                "frame": {"x":393,"y":129,"w":44,"h":17},
                "rotated": false,
                "trimmed": false,
                "spriteSourceSize": {"x":0,"y":0,"w":64,"h":65},
                "sourceSize": {"w":64,"h":63}
            },
            "worm_9":
            {
                "frame": {"x":441,"y":129,"w":44,"h":17},
                "rotated": false,
                "trimmed": false,
                "spriteSourceSize": {"x":0,"y":0,"w":64,"h":65},
                "sourceSize": {"w":64,"h":63}
            }
        },
        "hurt": {
            "worm_10":
            {
                "frame": {"x":20,"y":544,"w":23,"h":31},
                "rotated": false,
                "trimmed": false,
                "spriteSourceSize": {"x":0,"y":0,"w":64,"h":65},
                "sourceSize": {"w":64,"h":63}
            },
            "worm_11":
            {
                "frame": {"x":85,"y":544,"w":23,"h":31},
                "rotated": false,
                "trimmed": false,
                "spriteSourceSize": {"x":0,"y":0,"w":64,"h":65},
                "sourceSize": {"w":64,"h":63}
            },
            "worm_12":
            {
                "frame": {"x":146,"y":544,"w":23,"h":31},
                "rotated": false,
                "trimmed": false,
                "spriteSourceSize": {"x":0,"y":0,"w":64,"h":65},
                "sourceSize": {"w":64,"h":63}
            },
            "worm_13":
            {
                "frame": {"x":210,"y":544,"w":23,"h":31},
                "rotated": false,
                "trimmed": false,
                "spriteSourceSize": {"x":0,"y":0,"w":64,"h":65},
                "sourceSize": {"w":64,"h":63}
            },
            "worm_14":
            {
                "frame": {"x":276,"y":544,"w":23,"h":31},
                "rotated": false,
                "trimmed": false,
                "spriteSourceSize": {"x":0,"y":0,"w":64,"h":65},
                "sourceSize": {"w":64,"h":63}
            },
            "worm_15":
            {
                "frame": {"x":342,"y":544,"w":23,"h":31},
                "rotated": false,
                "trimmed": false,
                "spriteSourceSize": {"x":0,"y":0,"w":64,"h":65},
                "sourceSize": {"w":64,"h":63}
            }
        },
        "default": {
            "worm_15":
            {
                "frame": {"x":342,"y":544,"w":23,"h":31},
                "rotated": false,
                "trimmed": false,
                "spriteSourceSize": {"x":0,"y":0,"w":64,"h":65},
                "sourceSize": {"w":64,"h":63}
            }
        }, 
        "stop": {
            "worm_16":
            {
                "frame": {"x":342,"y":544,"w":23,"h":31},
                "rotated": false,
                "trimmed": false,
                "spriteSourceSize": {"x":0,"y":0,"w":64,"h":65},
                "sourceSize": {"w":64,"h":63}
            }
        },
        "combo": {
            "worm_17":
            {
                "frame": {"x":5,"y":396,"w":40,"h":42},
                "rotated": false,
                "trimmed": false,
                "spriteSourceSize": {"x":0,"y":0,"w":64,"h":65},
                "sourceSize": {"w":64,"h":63}  
            },
            "worm_18":
            {
                "frame": {"x":56,"y":396,"w":40,"h":42},
                "rotated": false,
                "trimmed": false,
                "spriteSourceSize": {"x":0,"y":0,"w":64,"h":65},
                "sourceSize": {"w":64,"h":63}  
            }, 
            "worm_19":
            {
                "frame": {"x":112,"y":396,"w":40,"h":42},
                "rotated": false,
                "trimmed": false,
                "spriteSourceSize": {"x":0,"y":0,"w":64,"h":65},
                "sourceSize": {"w":64,"h":63}  
            },
            "worm_20":
            {
                "frame": {"x":164,"y":396,"w":40,"h":42},
                "rotated": false,
                "trimmed": false,
                "spriteSourceSize": {"x":0,"y":0,"w":64,"h":65},
                "sourceSize": {"w":64,"h":63}  
            },
            "worm_21":
            {
                "frame": {"x":220,"y":396,"w":40,"h":42},
                "rotated": false,
                "trimmed": false,
                "spriteSourceSize": {"x":0,"y":0,"w":64,"h":65},
                "sourceSize": {"w":64,"h":63}  
            }, "worm_22":
            {
                "frame": {"x":276,"y":396,"w":40,"h":42},
                "rotated": false,
                "trimmed": false,
                "spriteSourceSize": {"x":0,"y":0,"w":64,"h":65},
                "sourceSize": {"w":64,"h":63}  
            }, "worm_23":
            {
                "frame": {"x":329,"y":396,"w":40,"h":42},
                "rotated": false,
                "trimmed": false,
                "spriteSourceSize": {"x":0,"y":0,"w":64,"h":65},
                "sourceSize": {"w":64,"h":63}  
            }, "worm_24":
            {
                "frame": {"x":382,"y":396,"w":40,"h":42},
                "rotated": false,
                "trimmed": false,
                "spriteSourceSize": {"x":0,"y":0,"w":64,"h":65},
                "sourceSize": {"w":64,"h":63}  
            }, "worm_25":
            {
                "frame": {"x":436,"y":396,"w":40,"h":42},
                "rotated": false,
                "trimmed": false,
                "spriteSourceSize": {"x":0,"y":0,"w":64,"h":65},
                "sourceSize": {"w":64,"h":63}  
            },"worm_26":
            {
                "frame": {"x":489,"y":396,"w":40,"h":42},
                "rotated": false,
                "trimmed": false,
                "spriteSourceSize": {"x":0,"y":0,"w":64,"h":65},
                "sourceSize": {"w":64,"h":63}  
            },"worm_27":
            {
                "frame": {"x":544,"y":396,"w":40,"h":42},
                "rotated": false,
                "trimmed": false,
                "spriteSourceSize": {"x":0,"y":0,"w":64,"h":65},
                "sourceSize": {"w":64,"h":63}  
            },"worm_28":
            {
                "frame": {"x":600,"y":396,"w":40,"h":42},
                "rotated": false,
                "trimmed": false,
                "spriteSourceSize": {"x":0,"y":0,"w":64,"h":65},
                "sourceSize": {"w":64,"h":63}  
            },"worm_29":
            {
                "frame": {"x":113,"y":462,"w":40,"h":42},
                "rotated": false,
                "trimmed": false,
                "spriteSourceSize": {"x":0,"y":0,"w":64,"h":65},
                "sourceSize": {"w":64,"h":63}  
            },"worm_30":
            {
                "frame": {"x":166,"y":462,"w":40,"h":42},
                "rotated": false,
                "trimmed": false,
                "spriteSourceSize": {"x":0,"y":0,"w":64,"h":65},
                "sourceSize": {"w":64,"h":63}  
            },
            "worm_31":
            {
                "frame": {"x":220,"y":462,"w":40,"h":42},
                "rotated": false,
                "trimmed": false,
                "spriteSourceSize": {"x":0,"y":0,"w":64,"h":65},
                "sourceSize": {"w":64,"h":63}  
            },
            "worm_32":
            {
                "frame": {"x":277,"y":462,"w":40,"h":42},
                "rotated": false,
                "trimmed": false,
                "spriteSourceSize": {"x":0,"y":0,"w":64,"h":65},
                "sourceSize": {"w":64,"h":63}  
            }
        },
        "jump": {
            "worm_33": {
                "frame": {"x":277,"y":462,"w":40,"h":42},
                "rotated": false,
                "trimmed": false,
                "spriteSourceSize": {"x":0,"y":0,"w":64,"h":65},
                "sourceSize": {"w":64,"h":63} 
            }
        }
    }
}